COPYING
README
ez_setup.py
setup.py
skel.py
skel.egg-info/PKG-INFO
skel.egg-info/SOURCES.txt
skel.egg-info/dependency_links.txt
skel.egg-info/entry_points.txt
skel.egg-info/top_level.txt
template1/+foo+/+bar+.txt.tpl
template1/+foo+/dontcopy
template1/+foo+/some+bar+/something.tpl
template2/+foo+/blargh.foo.tpl
template2/+foo+/some.jpg
