Metadata-Version: 1.0
Name: skel
Version: 0.3
Summary: Template-based filesystem manipulation (for project skeletons and such).
Home-page: http://lukearno.com/projects/skel/
Author: Luke Arno
Author-email: luke.arno@gmail.com
License: LGPL2
Keywords: directory filesystem project skel skeleton template command frameworks
Platform: UNKNOWN
Classifier: Development Status :: 3 - Alpha
Classifier: Intended Audience :: Developers
Classifier: License :: OSI Approved :: GNU Library or Lesser General Public License (LGPL)
Classifier: Natural Language :: English
Classifier: Operating System :: OS Independent
Classifier: Programming Language :: Python
Classifier: Topic :: Software Development :: Libraries
Classifier: Topic :: Utilities
